LICENSE
LICENSE.GPLv3
LICENSE.RPTv1
README.md
pyproject.toml
setup.cfg
setup.py
src/gdialog/__init__.py
src/gdialog/__main__.py
src/gdialog/dialog.c
src/gdialog.egg-info/PKG-INFO
src/gdialog.egg-info/SOURCES.txt
src/gdialog.egg-info/dependency_links.txt
src/gdialog.egg-info/top_level.txt
src/gdialog.egg-info/zip-safe
src/gdialog/pp/__init__.py