Metadata-Version: 2.4
Name: gdialog
Version: 0.50.0
Summary: gdialog - Simple Gtk Dialog
Author: Twinkle Computing
Author-email: Twinkle Computing <twinkle@twinkle.work>
License-Expression: GPL-3.0-or-later AND LicenseRef-ResistPsychiatricTerror-1.0-or-later
Project-URL: Homepage, https://github.com/ScrapWareOrg/gdialog
Project-URL: Issues, https://github.com/ScrapWareOrg/gdialog/issue
Classifier: Operating System :: OS Independent
Requires-Python: >=3.9
License-File: LICENSE
License-File: LICENSE.GPLv3
License-File: LICENSE.RPTv1
Dynamic: license-file
